[
    {
        "id": 1,
        "url": "https://s.yimg.com/ny/api/res/1.2/L9gejIRLvk5_Mizpk5FIjA--/YXBwaWQ9aGlnaGxhbmRlcjt3PTI0MDA7Y2Y9d2VicA--/https://media.zenfs.com/en/hearst_mens_health_171/418cf794813f409edbbcf5b22a6964a7",
        "description": ""
    },
    {
        "id": 2,
        "url": "https://wallpapercave.com/wp/wp10954207.jpg",
        "description": ""
    },
    {
        "id": 3,
        "url": "https://wallpapercave.com/wp/wp8243646.jpg",
        "description": ""
    },
    {
        "id": 4,
        "url": "https://wallpapercave.com/dwp1x/wp10954266.jpg",
        "description": ""
    },
    {
        "id": 5,
        "url": "",
        "description": ""
    },
    {
        "id": 6,
        "url": ""
    }
]